Metadata-Version: 2.1
Name: web3-account
Version: 1.0.1
Summary: The simplest way to use Web3 features
Home-page: https://github.com/langeth123/Web3Account
Download-URL: https://github.com/langeth123/Web3Account/archive/v1.0.1.zip
Author: lang123
Author-email: dima.lang3103@gmail.com
License: Apache License, Version 2.0, see LICENSE file
